model_bakery/__init__.py
model_bakery/_types.py
model_bakery/baker.py
model_bakery/content_types.py
model_bakery/exceptions.py
model_bakery/generators.py
model_bakery/gis.py
model_bakery/mock_file.txt
model_bakery/mock_img.jpeg
model_bakery/py.typed
model_bakery/random_gen.py
model_bakery/recipe.py
model_bakery/timezone.py
model_bakery/utils.py
model_bakery-1.23.2.dist-info/WHEEL
model_bakery-1.23.2.dist-info/METADATA
model_bakery-1.23.2.dist-info/RECORD
