Metadata-Version: 2.3
Name: model-bakery
Version: 1.23.2
Summary: Smart object creation facility for Django.
Keywords: django,factory,python,testing
Author: berin, amureki
Author-email: berin <bernardoxhc@gmail.com>, amureki <amureki@hey.com>
License: Apache License 2.0
Classifier: Development Status :: 5 - Production/Stable
Classifier: Framework :: Django
Classifier: Framework :: Django :: 4.2
Classifier: Framework :: Django :: 5.2
Classifier: Framework :: Django :: 6.0
Classifier: Intended Audience :: Developers
Classifier: License :: OSI Approved :: Apache Software License
Classifier: Operating System :: OS Independent
Classifier: Programming Language :: Python
Classifier: Programming Language :: Python :: 3
Classifier: Programming Language :: Python :: 3.10
Classifier: Programming Language :: Python :: 3.11
Classifier: Programming Language :: Python :: 3.12
Classifier: Programming Language :: Python :: 3.13
Classifier: Programming Language :: Python :: 3.14
Classifier: Topic :: Software Development
Requires-Dist: django>=4.2
Requires-Dist: sphinx ; extra == 'docs'
Requires-Dist: sphinx-rtd-theme ; extra == 'docs'
Requires-Dist: myst-parser ; extra == 'docs'
Requires-Python: >=3.10
Project-URL: Homepage, https://github.com/model-bakers/model_bakery
Provides-Extra: docs
